flox_git/__init__.py
flox_git/project.py
flox_git/workflow.py
flox_git-0.3.1.dist-info/entry_points.txt
flox_git-0.3.1.dist-info/LICENSE
flox_git-0.3.1.dist-info/WHEEL
flox_git-0.3.1.dist-info/METADATA
flox_git-0.3.1.dist-info/RECORD
